lib/__init__.py
lib/detector_prototype.py
lib/im2rec.py
lib/inference_prototype.py
monk_test1-0.0.7.dist-info/METADATA
monk_test1-0.0.7.dist-info/WHEEL
monk_test1-0.0.7.dist-info/top_level.txt
monk_test1-0.0.7.dist-info/RECORD
