Metadata-Version: 2.1
Name: monk-test1
Version: 0.0.7
Summary: A small example package
Home-page: https://github.com/pypa/sampleproject
Author: Example Author
Author-email: author@example.com
License: UNKNOWN
Platform: UNKNOWN
Classifier: Programming Language :: Python :: 3
Classifier: License :: OSI Approved :: Apache Software License
Classifier: Operating System :: OS Independent
Classifier: Environment :: GPU :: NVIDIA CUDA :: 9.0
Requires-Python: >=3.6
Requires-Dist: requests
Requires-Dist: numpy (==1.19.0)
